logicmonitor_data_sdk/__init__.py
logicmonitor_data_sdk/api_client.py
logicmonitor_data_sdk/configuration.py
logicmonitor_data_sdk/rest.py
logicmonitor_data_sdk/version.py
logicmonitor_data_sdk/api/__init__.py
logicmonitor_data_sdk/api/logs.py
logicmonitor_data_sdk/api/metrics.py
logicmonitor_data_sdk/api/response_interface.py
logicmonitor_data_sdk/internal/__init__.py
logicmonitor_data_sdk/internal/internal_cache.py
logicmonitor_data_sdk/models/__init__.py
logicmonitor_data_sdk/models/datapoint.py
logicmonitor_data_sdk/models/datasource.py
logicmonitor_data_sdk/models/datasource_instance.py
logicmonitor_data_sdk/models/list_rest_data_point_v1.py
logicmonitor_data_sdk/models/list_rest_data_source_instance_v1.py
logicmonitor_data_sdk/models/map_string_string.py
logicmonitor_data_sdk/models/push_metric_api_response.py
logicmonitor_data_sdk/models/resource.py
logicmonitor_data_sdk/models/rest_data_point_v1.py
logicmonitor_data_sdk/models/rest_data_source_instance_v1.py
logicmonitor_data_sdk/models/rest_instance_properties_v1.py
logicmonitor_data_sdk/models/rest_metrics_v1.py
logicmonitor_data_sdk/models/rest_resource_properties_v1.py
logicmonitor_data_sdk/utils/__init__.py
logicmonitor_data_sdk/utils/object_name_validator.py
logicmonitor_data_sdk-0.0.9b3.dist-info/licenses/LICENSE
test/__init__.py
test/test_api_client.py
test/test_configuration.py
test/test_example.py
test/test_one_requests.py
test/test_requests.py
test/test_rest.py
test/internal/__init__.py
test/internal/test_internal_cache.py
test/models/__init__.py
test/models/test_datapoint.py
test/models/test_datasource.py
test/models/test_datasource_instance.py
test/models/test_list_rest_data_point_v1.py
test/models/test_list_rest_data_source_instance_v1.py
test/models/test_map_string_string.py
test/models/test_push_metric_api_response.py
test/models/test_resource.py
test/models/test_rest_data_point_v1.py
test/models/test_rest_data_source_instance_v1.py
test/models/test_rest_instance_properties_v1.py
test/models/test_rest_metrics_v1.py
logicmonitor_data_sdk-0.0.9b3.dist-info/METADATA
logicmonitor_data_sdk-0.0.9b3.dist-info/WHEEL
logicmonitor_data_sdk-0.0.9b3.dist-info/top_level.txt
logicmonitor_data_sdk-0.0.9b3.dist-info/RECORD
