Metadata-Version: 2.4
Name: logicmonitor_data_sdk
Version: 0.0.9b3
Summary: LogicMonitor Rest API
Author: LogicMonitor
Author-email: support@logicmonitor.com
Project-URL: Documentation, https://logicmonitor-data-sdk-py.readthedocs.io/en/latest/
Project-URL: Tracker, https://github.com/logicmonitor/logicmonitor_data_sdk_py/issues
Classifier: Development Status :: 4 - Beta
Classifier: Operating System :: OS Independent
Classifier: Intended Audience :: Developers
Classifier: Programming Language :: Python :: 2.7
Classifier: Programming Language :: Python :: 3.4
Requires-Python: >=3.4,>=2.7
License-File: LICENSE
Requires-Dist: urllib3>=1.15
Requires-Dist: six>=1.10
Requires-Dist: certifi
Requires-Dist: python-dateutil
Dynamic: author
Dynamic: author-email
Dynamic: classifier
Dynamic: description
Dynamic: description-content-type
Dynamic: license-file
Dynamic: project-url
Dynamic: requires-dist
Dynamic: requires-python
Dynamic: summary
